antipode/__init__.py
antipode/anndata_utils.py
antipode/antipode_mixins.py
antipode/antipode_model.py
antipode/model_distributions.py
antipode/model_functions.py
antipode/model_modules.py
antipode/phylo.py
antipode/plotting.py
antipode/post.py
antipode/train_utils.py
antipode-0.1.0.dist-info/licenses/LICENSE
tests/__init__.py
antipode-0.1.0.dist-info/METADATA
antipode-0.1.0.dist-info/WHEEL
antipode-0.1.0.dist-info/top_level.txt
antipode-0.1.0.dist-info/RECORD
