Metadata-Version: 2.4
Name: antipode
Version: 0.1.0
Summary: Simultaneous integration, differential expression and clustering of single cell RNAseq data using pyro-powered variational inference.
Author: Matthew Schmitz
Project-URL: Source, https://github.com/mtvector/scANTIPODE
Classifier: Programming Language :: Python :: 3.12
Classifier: Topic :: Scientific/Engineering :: Bio-Informatics
Requires-Python: >=3.10
License-File: LICENSE
Requires-Dist: scanpy
Requires-Dist: scvi-tools
Requires-Dist: pyro-ppl
Requires-Dist: seaborn
Requires-Dist: scikit-learn
Requires-Dist: legacy-cgi
Requires-Dist: ete3
Requires-Dist: glasbey
Provides-Extra: extras
Requires-Dist: biopython; extra == "extras"
Requires-Dist: gseapy; extra == "extras"
Requires-Dist: PyComplexHeatmap; extra == "extras"
Requires-Dist: glasbey; extra == "extras"
Dynamic: license-file
